examples/animate_cam_light.py
examples/animate_rotating.py
examples/concurrent_run.py
examples/export_import_usd.py
examples/scene_show.py
examples/scene_themes.py
pycg/__init__.py
pycg/animation.py
pycg/blender_client.py
pycg/camera.py
pycg/color.py
pycg/exp.py
pycg/html.py
pycg/image.py
pycg/interfaces.py
pycg/isometry.py
pycg/nas.py
pycg/o3d.py
pycg/pdf.py
pycg/render.py
pycg/video.py
pycg/vis.py
pycg/wdb.py
pycg/assets/uv.png
pycg/assets/envmaps/gtc.png
pycg/assets/envmaps/pycg-gtc_ibl.ktx
pycg/assets/envmaps/pycg-gtc_skybox.ktx
pycg/assets/envmaps/pycg-rainforest_ibl.ktx
pycg/assets/envmaps/pycg-rainforest_skybox.ktx
pycg/assets/envmaps/rainforest.hdr
pycg/blender_server/assets.py
pycg/blender_server/main.py
pycg/blender_server/style.py
python_pycg-1.0.1.dist-info/licenses/LICENSE
python_pycg-1.0.1.dist-info/METADATA
python_pycg-1.0.1.dist-info/WHEEL
python_pycg-1.0.1.dist-info/top_level.txt
python_pycg-1.0.1.dist-info/RECORD
