Metadata-Version: 2.4
Name: python-pycg
Version: 1.0.1
Summary: PyCG: Toolbox for CG-related visualizations and computations
Author-email: Jiahui Huang <huangjh.work@outlook.com>
License: MIT
Project-URL: Homepage, https://github.com/heiwang1997/pycg
Project-URL: Repository, https://github.com/heiwang1997/pycg
Keywords: pycg,graphics,3d,visualization
Classifier: Operating System :: Unix
Classifier: Topic :: Multimedia :: Graphics
Classifier: License :: OSI Approved :: MIT License
Classifier: Programming Language :: Python :: 3 :: Only
Requires-Python: >=3.6
License-File: LICENSE
Requires-Dist: numpy
Requires-Dist: matplotlib
Requires-Dist: pyquaternion
Requires-Dist: pyyaml
Requires-Dist: omegaconf
Requires-Dist: tqdm
Requires-Dist: pynvml
Requires-Dist: calmsize
Requires-Dist: rich
Requires-Dist: plyfile
Requires-Dist: trimesh
Requires-Dist: imageio
Requires-Dist: screeninfo
Requires-Dist: pillow
Requires-Dist: usd-core
Requires-Dist: scipy
Provides-Extra: all
Requires-Dist: open3d_pycg_cpu; extra == "all"
Dynamic: license-file
